connlp/__init__.py
connlp/analysis.py
connlp/analysis_lda.py
connlp/analysis_ner.py
connlp/embedding.py
connlp/preprocess.py
connlp/test.py
connlp/text_extract.py
connlp/util.py
connlp/visualize.py
connlp/web_crawling.py
constrnlp/__init__.py
constrnlp/embedding.py
constrnlp/merong.py
constrnlp/preprocess.py
constrnlp/test.py
constrnlp/util.py
constrnlp/visualize.py
constrnlp/thesaurus/__init__.py
connlp-0.0.18.dist-info/METADATA
connlp-0.0.18.dist-info/WHEEL
connlp-0.0.18.dist-info/top_level.txt
connlp-0.0.18.dist-info/RECORD
