Metadata-Version: 2.1
Name: connlp
Version: 0.0.18
Summary: A bunch of python codes to analyze text data in the construction industry. Mainly reconstitute the pre-exist python libraries for Natural Language Processing (NLP)
Home-page: https://github.com/blank54/connlp.git
Author: Seonghyeon Boris Moon
Author-email: boris.moon514@gmail.com
License: UNKNOWN
Platform: UNKNOWN
